twitchpy/__init__.py
twitchpy/bot.py
twitchpy/client.py
twitchpy/errors.py
twitchpy/_api/__init__.py
twitchpy/_api/ads.py
twitchpy/_api/analytics.py
twitchpy/_api/bits.py
twitchpy/_api/channels.py
twitchpy/_api/charity_campaigns.py
twitchpy/_api/chats.py
twitchpy/_api/clips.py
twitchpy/_api/content_classification_labels.py
twitchpy/_api/drops.py
twitchpy/_api/eventsubs.py
twitchpy/_api/extensions.py
twitchpy/_api/games.py
twitchpy/_api/goals.py
twitchpy/_api/guest_stars.py
twitchpy/_api/hype_trains.py
twitchpy/_api/moderation.py
twitchpy/_api/polls.py
twitchpy/_api/predictions.py
twitchpy/_api/raids.py
twitchpy/_api/rewards.py
twitchpy/_api/schedules.py
twitchpy/_api/searchs.py
twitchpy/_api/streams.py
twitchpy/_api/subscriptions.py
twitchpy/_api/tags.py
twitchpy/_api/teams.py
twitchpy/_api/users.py
twitchpy/_api/videos.py
twitchpy/_api/whispers.py
twitchpy/_utils/__init__.py
twitchpy/_utils/date.py
twitchpy/_utils/http.py
twitchpy/dataclasses/__init__.py
twitchpy/dataclasses/ad_schedule.py
twitchpy/dataclasses/automod_settings.py
twitchpy/dataclasses/badge.py
twitchpy/dataclasses/badge_version.py
twitchpy/dataclasses/banned_user.py
twitchpy/dataclasses/bits_leaderboard_leader.py
twitchpy/dataclasses/blocked_term.py
twitchpy/dataclasses/channel.py
twitchpy/dataclasses/charity_campaign.py
twitchpy/dataclasses/charity_campaign_amount.py
twitchpy/dataclasses/charity_campaign_donation.py
twitchpy/dataclasses/chat_settings.py
twitchpy/dataclasses/chatter_warning.py
twitchpy/dataclasses/cheermote.py
twitchpy/dataclasses/cheermote_tier.py
twitchpy/dataclasses/clip.py
twitchpy/dataclasses/commercial.py
twitchpy/dataclasses/conduit.py
twitchpy/dataclasses/conduit_shard.py
twitchpy/dataclasses/content_classification_label.py
twitchpy/dataclasses/creator_goal.py
twitchpy/dataclasses/drop_entitlement.py
twitchpy/dataclasses/emote.py
twitchpy/dataclasses/eventsub_subscription.py
twitchpy/dataclasses/extension.py
twitchpy/dataclasses/extension_analytics_report.py
twitchpy-1.3.2.dist-info/LICENSE
twitchpy-1.3.2.dist-info/METADATA
twitchpy-1.3.2.dist-info/WHEEL
twitchpy-1.3.2.dist-info/top_level.txt
twitchpy-1.3.2.dist-info/RECORD
