Metadata-Version: 2.2
Name: twitchpy
Version: 1.3.2
Summary: TwitchPy is a Python package for using the Twitch's API and create bots for interacting with their IRC chats.
Author-email: DaCasBe <dacasbe97@gmail.com>
License: GNU GENERAL PUBLIC LICENSE
Project-URL: Homepage, https://github.com/DaCasBe/TwitchPy
Requires-Python: >=3.10
License-File: LICENSE
Requires-Dist: requests
